python_overseerr/__init__.py
python_overseerr/exceptions.py
python_overseerr/models.py
python_overseerr/overseerr.py
python_overseerr/py.typed
python_overseerr-0.8.0.dist-info/METADATA
python_overseerr-0.8.0.dist-info/WHEEL
python_overseerr-0.8.0.dist-info/licenses/LICENSE.md
python_overseerr-0.8.0.dist-info/RECORD
